[{
    "phone": "13153185002",
    "pass": "123456",
    "addressId": 1893802
}, {
    "phone": "13343192376",
    "pass": "123456",
    "addressId": 1885157
}, {
    "phone": "13485665212",
    "pass": "123456",
    "addressId": 1676457
}, {
    "phone": "13700077519",
    "pass": "123456",
    "addressId": 1892989
}, {
    "phone": "15063527328",
    "pass": "123456",
    "addressId": 1893768
}, {
    "phone": "15075870950",
    "pass": "123456",
    "addressId": 1712578
}, {
    "phone": "15206334886",
    "pass": "123456",
    "addressId": 1903115
}, {
    "phone": "15303199414",
    "pass": "123456",
    "addressId": 1885243
}, {
    "phone": "15354193781",
    "pass": "123456",
    "addressId": 1879769
}, {
    "phone": "15373204143",
    "pass": "123456",
    "addressId": 1885212
}, {
    "phone": "15399130078",
    "pass": "125018adg",
    "addressId": 1697988
}, {
    "phone": "15515970953",
    "pass": "123456",
    "addressId": 1843374
}, {
    "phone": "15627944858",
    "pass": "123456",
    "addressId": 1894176
}, {
    "phone": "15937230461",
    "pass": "123456",
    "addressId": 1845446
}, {
    "phone": "15951853170",
    "pass": "123456",
    "addressId": 1885124
}, {
    "phone": "17379324087",
    "pass": "123456",
    "addressId": 1858864
}, {
    "phone": "18353874500",
    "pass": "anjiaqi112828",
    "addressId": 1787812
}, {
    "phone": "18537303412",
    "pass": "z410781"
}, {
    "phone": "13464686175",
    "pass": "a123456",
    "addressId": 1951713
}, {
    "phone": "17853697903",
    "pass": "a123456",
    "addressId": 1951715
}, {
    "phone": "18864854877",
    "pass": "a123456",
    "addressId": 1951722
}, {
    "phone": "13463414918",
    "pass": "a123456",
    "addressId": 1951723
}, {
    "phone": "15835086989",
    "pass": "a123456",
    "addressId": 1951725
}, {
    "phone": "17393232815",
    "pass": "a123456",
    "addressId": ""
}, {
    "phone": "15665166293",
    "pass": "a123456",
    "addressId": 1951731
}, {
    "phone": "15830750275",
    "pass": "a123456"
}, {
    "phone": "18743635726",
    "pass": "a123456",
    "addressId": 1951735
}, {
    "phone": "18698817813",
    "pass": "a123456",
    "addressId": 1951753
}, {
    "phone": "13081312422",
    "pass": "a123456",
    "addressId": 1951801
}, {
    "phone": "17631880252",
    "pass": "a123456",
    "addressId": 1951813
}, {
    "phone": "13333176802",
    "pass": "a123456",
    "addressId": 1930785
}, {
    "phone": "13593493641",
    "pass": "a123456",
    "addressId": 1930789
}, {
    "phone": "15613794675",
    "pass": "a123456"
}, {
    "phone": "13670589613",
    "pass": "a123456",
    "addressId": 1930705
}, {
    "phone": "13102661153",
    "pass": "123456",
    "addressId": 1698680
}, {
    "phone": "17535275750",
    "pass": "123456",
    "addressId": 1892886
}, {
    "phone": "13336323159",
    "pass": "4063443",
    "addressId": 1935794
}, {
    "phone": "13351208936",
    "pass": "jss19860529",
    "addressId": 1935795
}, {
    "phone": "13399381732",
    "pass": "q123456",
    "addressId": 1935796
}, {
    "phone": "13519083633",
    "pass": "q123456",
    "addressId": 1935798
}, {
    "phone": "13521690981",
    "pass": "123456",
    "addressId": 1935799
}, {
    "phone": "13546886639",
    "pass": "qin141208",
    "addressId": 1935801
}, {
    "phone": "13633696711",
    "pass": "w070416",
    "addressId": 1935803
}, {
    "phone": "13764763451",
    "pass": "123456"
}, {
    "phone": "13938038163",
    "pass": "123456",
    "addressId": 1935805
}, {
    "phone": "13993852417",
    "pass": "q123456",
    "addressId": 1935806
}, {
    "phone": "15039586436",
    "pass": "123456",
    "addressId": 1935807
}, {
    "phone": "15102549597",
    "pass": "ml080727",
    "addressId": 1935808
}, {
    "phone": "15131828567",
    "pass": "123456",
    "addressId": 1935809
}, {
    "phone": "15264711001",
    "pass": "123456",
    "addressId": 1935811
}, {
    "phone": "15393630594",
    "pass": "123456",
    "addressId": 1935813
}, {
    "phone": "15633523066",
    "pass": "abc123",
    "addressId": 1935815
}, {
    "phone": "15699770933",
    "pass": "123456",
    "addressId": 1935816
}, {
    "phone": "15949806339",
    "pass": "lhj0325",
    "addressId": 1935818
}, {
    "phone": "17097224268",
    "pass": "123456",
    "addressId": 1894299
}, {
    "phone": "17612746321",
    "pass": "123456321654",
    "addressId": 1935820
}, {
    "phone": "18032952504",
    "pass": "123456"
}, {
    "phone": "18201603185",
    "pass": "123456",
    "addressId": 1884119
}, {
    "phone": "18207517996",
    "pass": "123456",
    "addressId": 1829922
}, {
    "phone": "18333966217",
    "pass": "123456",
    "addressId": 1879800
}, {
    "phone": "18382394514",
    "pass": "123456",
    "addressId": 1840503
}, {
    "phone": "18629896680",
    "pass": "123456",
    "addressId": 1872179
}, {
    "phone": "18946959184",
    "pass": "123456",
    "addressId": 1893645
}, {
    "phone": "13157440883",
    "pass": "123456"
}, {
    "phone": "18593078244",
    "pass": "a123456",
    "addressId": 1961823
}, {
    "phone": "13052107547",
    "pass": "a123456",
    "addressId": 1961828
}, {
    "phone": "13969577793",
    "pass": "a123456",
    "addressId": 1961829
}, {
    "phone": "15835843109",
    "pass": "a123456",
    "addressId": 1961832
}, {
    "phone": "15535874823",
    "pass": "a123456",
    "addressId": 1961833
}, {
    "phone": "15525146023",
    "pass": "a123456",
    "addressId": 1961836
}, {
    "phone": "15808729122",
    "pass": "a123456",
    "addressId": 1961837
}, {
    "phone": "18735426089",
    "pass": "a123456",
    "addressId": 1961843
}, {
    "phone": "18734572393",
    "pass": "a123456",
    "addressId": 1961844
}, {
    "phone": "15582882641",
    "pass": "a123456",
    "addressId": 1961845
}, {
    "phone": "13103589823",
    "pass": "a123456",
    "addressId": 1961848
}, {
    "phone": "15564917183",
    "pass": "a123456",
    "addressId": 1961852
}, {
    "phone": "15588159966",
    "pass": "a123456",
    "addressId": 1961854
}, {
    "phone": "13619167945",
    "pass": "a123456",
    "addressId": 1961857
}, {
    "phone": "18545086596",
    "pass": "a123456",
    "addressId": 1961858
}, {
    "phone": "17732510974",
    "pass": "a123456",
    "addressId": 1961859
}, {
    "phone": "18241816845",
    "pass": "a123456",
    "addressId": 1961860
}, {
    "phone": "15682637686",
    "pass": "a123456",
    "addressId": 1961861
}, {
    "phone": "15725878435",
    "pass": "a123456"
}, {
    "phone": "15934072914",
    "pass": "a123456",
    "addressId": 1961865
}, {
    "phone": "18909564220",
    "pass": "a123456",
    "addressId": 1961867
}, {
    "phone": "15660773191",
    "pass": "a123456",
    "addressId": 1961868
}, {
    "phone": "17073020029",
    "pass": "a123456"
}, {
    "phone": "15386030922",
    "pass": "a123456",
    "addressId": 1961872
}, {
    "phone": "15535890431",
    "pass": "a123456",
    "addressId": 1961873
}, {
    "phone": "15303529430",
    "pass": "a123456",
    "addressId": 1961875
}, {
    "phone": "17635568238",
    "pass": "a123456",
    "addressId": 1961943
}, {
    "phone": "15535486077",
    "pass": "a123456",
    "addressId": 1961944
}, {
    "phone": "18754955373",
    "pass": "a123456",
    "addressId": 1961946
}, {
    "phone": "13969995407",
    "pass": "a123456"
}, {
    "phone": "18154567585",
    "pass": "a123456",
    "addressId": 1961948
}, {
    "phone": "15834343940",
    "pass": "a123456",
    "addressId": 1961950
}, {
    "phone": "17196748368",
    "pass": "a123456",
    "addressId": 1961953
}, {
    "phone": "13781072791",
    "pass": "a123456",
    "addressId": 1961955
}, {
    "phone": "17031887830",
    "pass": "a123456",
    "addressId": 1962177
}, {
    "phone": "15141626707",
    "pass": "a123456",
    "addressId": 1962181
}, {
    "phone": "15042695614",
    "pass": "a123456",
    "addressId": 1962183
}, {
    "phone": "15076039887",
    "pass": "a123456",
    "addressId": 1962185
}, {
    "phone": "15533586119",
    "pass": "a123456",
    "addressId": ""
}, {
    "phone": "15046800490",
    "pass": "a123456",
    "addressId": 1962190
}, {
    "phone": "18735798509",
    "pass": "a123456",
    "addressId": 1962193
}, {
    "phone": "15584909806",
    "pass": "a123456",
    "addressId": 1962194
}, {
    "phone": "17631643045",
    "pass": "a123456",
    "addressId": 1962196
}, {
    "phone": "13500156546",
    "pass": "a123456",
    "addressId": 1951756
}, {
    "phone": "15364585915",
    "pass": "a123456",
    "addressId": 1962198
}, {
    "phone": "15053052761",
    "pass": "a123456",
    "addressId": 1962199
}, {
    "phone": "17844202122",
    "pass": "a123456",
    "addressId": 1962200
}, {
    "phone": "18365799221",
    "pass": "a123456",
    "addressId": ""
}, {
    "phone": "18435817238",
    "pass": "a123456",
    "addressId": 1962202
}, {
    "phone": "13831322890",
    "pass": "a123456",
    "addressId": 1962203
}, {
    "phone": "17601643138",
    "pass": "a123456",
    "addressId": 1962207
}, {
    "phone": "15612145727",
    "pass": "a123456",
    "addressId": 1962208
}, {
    "phone": "13220790090",
    "pass": "a123456",
    "addressId": 1962209
}, {
    "phone": "15003443253",
    "pass": "a123456",
    "addressId": 1962214
}, {
    "phone": "17131970724",
    "pass": "a123456",
    "addressId": 1962215
}, {
    "phone": "15319647574",
    "pass": "a123456",
    "addressId": 1969314
}, {
    "phone": "17667374197",
    "pass": "a123456",
    "addressId": 1962216
}, {
    "phone": "17603803317",
    "pass": "a123456",
    "addressId": 1962217
}, {
    "phone": "13676343367",
    "pass": "a123456",
    "addressId": 1962219
}, {
    "phone": "15257918657",
    "pass": "a123456",
    "addressId": 1962220
}, {
    "phone": "17539236327",
    "pass": "a123456",
    "addressId": 1962226
}, {
    "phone": "15039298864",
    "pass": "a123456",
    "addressId": 1962228
}, {
    "phone": "13839228541",
    "pass": "a123456",
    "addressId": 1962229
}, {
    "phone": "15964388967",
    "pass": "a123456",
    "addressId": ""
}, {
    "phone": "15733586109",
    "pass": "a123456",
    "addressId": 1962231
}, {
    "phone": "17364621646",
    "pass": "a123456",
    "addressId": ""
}, {
    "phone": "15193524480",
    "pass": "a123456",
    "addressId": ""
}, {
    "phone": "13316547635",
    "pass": "a123456",
    "addressId": 1962235
}, {
    "phone": "18818426811",
    "pass": "a123456",
    "addressId": 1962236
}, {
    "phone": "15034681449",
    "pass": "a123456",
    "addressId": 1962237
}, {
    "phone": "15133355337",
    "pass": "a123456",
    "addressId": 1962238
}, {
    "phone": "15257918657",
    "pass": "a123456",
    "addressId": 1962220
}, {
    "phone": "17833954615",
    "pass": "a123456",
    "addressId": 1962240
}, {
    "phone": "18331375226",
    "pass": "a123456",
    "addressId": ""
}, {
    "phone": "18256710448",
    "pass": "a123456",
    "addressId": 1961877
}]