{"www.cmaotai.com":{"/":{"acw_tc":{"key":"acw_tc","value":"AQAAAEXRygSeIAoA6l5H311/0eD35YQy","domain":"www.cmaotai.com","path":"/","httpOnly":true,"hostOnly":true,"creation":"2018-05-24T00:00:58.334Z","lastAccessed":"2018-05-24T00:00:58.334Z"},"ASP.NET_SessionId":{"key":"ASP.NET_SessionId","value":"hkvgx43t0icyf51q20nk0tyu","domain":"www.cmaotai.com","path":"/","httpOnly":true,"hostOnly":true,"creation":"2018-05-24T00:00:58.334Z","lastAccessed":"2018-05-24T00:00:58.334Z"},"Vshop-Member":{"key":"Vshop-Member","value":"674a604be7434baca8184b5c0f12a9b3","expires":"2019-05-24T00:00:16.000Z","domain":"www.cmaotai.com","path":"/","hostOnly":true,"creation":"2018-05-24T00:00:58.334Z","lastAccessed":"2018-05-24T00:00:58.334Z"},"SERVERID":{"key":"SERVERID","value":"2fa397870239218a49136d91e984b8ea|1527120016|1527120016","domain":"www.cmaotai.com","path":"/","hostOnly":true,"creation":"2018-05-24T00:00:58.334Z","lastAccessed":"2018-05-24T00:00:58.334Z"}}}}