{"www.cmaotai.com":{"/":{"acw_tc":{"key":"acw_tc","value":"AQAAAPCrzQ4cwwcATuwic763u9d4pEYG","domain":"www.cmaotai.com","path":"/","httpOnly":true,"hostOnly":true,"creation":"2018-05-20T09:40:27.579Z","lastAccessed":"2018-05-20T09:40:27.579Z"},"ASP.NET_SessionId":{"key":"ASP.NET_SessionId","value":"e2xoygnuzerqzna1tnm5enwp","domain":"www.cmaotai.com","path":"/","httpOnly":true,"hostOnly":true,"creation":"2018-05-20T09:40:27.579Z","lastAccessed":"2018-05-20T09:40:27.579Z"},"Vshop-Member":{"key":"Vshop-Member","value":"aa4d918c83884a4cb7d730a57bb2e07c","expires":"2019-05-20T09:40:27.000Z","domain":"www.cmaotai.com","path":"/","hostOnly":true,"creation":"2018-05-20T09:40:27.579Z","lastAccessed":"2018-05-20T09:40:27.579Z"},"SERVERID":{"key":"SERVERID","value":"73717107c680adffd3c04c75b05bf592|1526809227|1526809227","domain":"www.cmaotai.com","path":"/","hostOnly":true,"creation":"2018-05-20T09:40:27.580Z","lastAccessed":"2018-05-20T09:40:27.580Z"}}}}