{"www.cmaotai.com":{"/":{"acw_tc":{"key":"acw_tc","value":"AQAAABEhtUrPdwsATuwic0ysJiN5hF+m","domain":"www.cmaotai.com","path":"/","httpOnly":true,"hostOnly":true,"creation":"2018-05-20T09:40:28.940Z","lastAccessed":"2018-05-20T09:40:28.940Z"},"ASP.NET_SessionId":{"key":"ASP.NET_SessionId","value":"o5zj24jmb5tqdh2asd1jbtym","domain":"www.cmaotai.com","path":"/","httpOnly":true,"hostOnly":true,"creation":"2018-05-20T09:40:28.940Z","lastAccessed":"2018-05-20T09:40:28.940Z"},"Vshop-Member":{"key":"Vshop-Member","value":"4414ea018a16476b9e4533346ca1b351","expires":"2019-05-20T09:40:28.000Z","domain":"www.cmaotai.com","path":"/","hostOnly":true,"creation":"2018-05-20T09:40:28.941Z","lastAccessed":"2018-05-20T09:40:28.941Z"},"SERVERID":{"key":"SERVERID","value":"2fa397870239218a49136d91e984b8ea|1526809228|1526809228","domain":"www.cmaotai.com","path":"/","hostOnly":true,"creation":"2018-05-20T09:40:28.941Z","lastAccessed":"2018-05-20T09:40:28.941Z"}}}}