{"www.cmaotai.com":{"/":{"acw_tc":{"key":"acw_tc","value":"AQAAAOKF7CAX+ggA6l5H357AP6jozCAw","domain":"www.cmaotai.com","path":"/","httpOnly":true,"hostOnly":true,"creation":"2018-05-29T00:51:10.592Z","lastAccessed":"2018-05-29T00:51:10.592Z"},"ASP.NET_SessionId":{"key":"ASP.NET_SessionId","value":"ebg5cv5lqdh3wpqvexzytpgm","domain":"www.cmaotai.com","path":"/","httpOnly":true,"hostOnly":true,"creation":"2018-05-29T00:51:10.592Z","lastAccessed":"2018-05-29T00:51:10.592Z"},"Vshop-Member":{"key":"Vshop-Member","value":"4a93b18ae8694d44bc03ca340efc052e","expires":"2019-05-29T00:51:10.000Z","domain":"www.cmaotai.com","path":"/","hostOnly":true,"creation":"2018-05-29T00:51:10.592Z","lastAccessed":"2018-05-29T00:51:10.592Z"},"SERVERID":{"key":"SERVERID","value":"19df48d02d2df737cbba18bd9d142364|1527555070|1527555070","domain":"www.cmaotai.com","path":"/","hostOnly":true,"creation":"2018-05-29T00:51:10.592Z","lastAccessed":"2018-05-29T00:51:10.592Z"}}}}