{"www.cmaotai.com":{"/":{"acw_tc":{"key":"acw_tc","value":"AQAAAI+5SHCnWwcA6l5H31TRwXqc5dnS","domain":"www.cmaotai.com","path":"/","httpOnly":true,"hostOnly":true,"creation":"2018-05-29T00:51:14.456Z","lastAccessed":"2018-05-29T00:51:14.456Z"},"ASP.NET_SessionId":{"key":"ASP.NET_SessionId","value":"yrbycqx4bm3jlyp145vsgogg","domain":"www.cmaotai.com","path":"/","httpOnly":true,"hostOnly":true,"creation":"2018-05-29T00:51:14.456Z","lastAccessed":"2018-05-29T00:51:14.456Z"},"Vshop-Member":{"key":"Vshop-Member","value":"8af31c2ebd144084bdd90bec771118e5","expires":"2019-05-29T00:51:14.000Z","domain":"www.cmaotai.com","path":"/","hostOnly":true,"creation":"2018-05-29T00:51:14.456Z","lastAccessed":"2018-05-29T00:51:14.456Z"},"SERVERID":{"key":"SERVERID","value":"8438f30ad0357ca7b03a23fe6e9923a1|1527555074|1527555074","domain":"www.cmaotai.com","path":"/","hostOnly":true,"creation":"2018-05-29T00:51:14.456Z","lastAccessed":"2018-05-29T00:51:14.456Z"}}}}