{"www.cmaotai.com":{"/":{"acw_tc":{"key":"acw_tc","value":"AQAAAE4VxH7y4gQA85LVc3Sq5T+VpkNv","domain":"www.cmaotai.com","path":"/","httpOnly":true,"hostOnly":true,"creation":"2018-04-25T08:41:10.392Z","lastAccessed":"2018-04-25T08:41:10.392Z"},"ASP.NET_SessionId":{"key":"ASP.NET_SessionId","value":"auhaskf2isp4i3sjvxzie4ox","domain":"www.cmaotai.com","path":"/","httpOnly":true,"hostOnly":true,"creation":"2018-04-25T08:41:10.396Z","lastAccessed":"2018-04-25T08:41:10.396Z"},"Vshop-Member":{"key":"Vshop-Member","value":"4b307fe7d9c247bebd02a34cfac8702f","expires":"2019-04-25T08:41:10.000Z","domain":"www.cmaotai.com","path":"/","hostOnly":true,"creation":"2018-04-25T08:41:10.399Z","lastAccessed":"2018-04-25T08:41:10.399Z"},"SERVERID":{"key":"SERVERID","value":"e0be7116fc95174c0c92660b6cc51b85|1524645670|1524645670","domain":"www.cmaotai.com","path":"/","hostOnly":true,"creation":"2018-04-25T08:41:10.400Z","lastAccessed":"2018-04-25T08:41:10.400Z"}}}}