{"www.cmaotai.com":{"/":{"acw_tc":{"key":"acw_tc","value":"AQAAAJTrkh2wBwQAkaizbwj6XUdpr6RI","domain":"www.cmaotai.com","path":"/","httpOnly":true,"hostOnly":true,"creation":"2018-04-12T15:31:44.426Z","lastAccessed":"2018-04-12T15:31:44.426Z"},"ASP.NET_SessionId":{"key":"ASP.NET_SessionId","value":"uodjmg1srzsrsnrnznzu0m1l","domain":"www.cmaotai.com","path":"/","httpOnly":true,"hostOnly":true,"creation":"2018-04-12T15:31:44.426Z","lastAccessed":"2018-04-12T15:31:44.426Z"},"Vshop-Member":{"key":"Vshop-Member","value":"4091b249ab7e4dbe9a29d2115439ecef","expires":"2019-04-12T15:31:44.000Z","domain":"www.cmaotai.com","path":"/","hostOnly":true,"creation":"2018-04-12T15:31:44.426Z","lastAccessed":"2018-04-12T15:31:44.426Z"},"SERVERID":{"key":"SERVERID","value":"f8ea4c3ae1c03eb905c9ff5aec4903d9|1523547104|1523547104","domain":"www.cmaotai.com","path":"/","hostOnly":true,"creation":"2018-04-12T15:31:44.427Z","lastAccessed":"2018-04-12T15:31:44.427Z"}}}}