{"www.cmaotai.com":{"/":{"acw_tc":{"key":"acw_tc","value":"AQAAAK/4FG/qngIAWKTbc9jUDiNUPkf8","domain":"www.cmaotai.com","path":"/","httpOnly":true,"hostOnly":true,"creation":"2018-04-04T05:06:44.272Z","lastAccessed":"2018-04-04T05:06:44.272Z"},"ASP.NET_SessionId":{"key":"ASP.NET_SessionId","value":"v33lrs2hmphzd3yoradtcq2w","domain":"www.cmaotai.com","path":"/","httpOnly":true,"hostOnly":true,"creation":"2018-04-04T05:06:44.273Z","lastAccessed":"2018-04-04T05:06:44.273Z"},"Vshop-Member":{"key":"Vshop-Member","value":"a43b7ddadc404184a613a77659d2bd13","expires":"2019-04-04T05:06:41.000Z","domain":"www.cmaotai.com","path":"/","hostOnly":true,"creation":"2018-04-04T05:06:44.273Z","lastAccessed":"2018-04-04T05:06:44.273Z"},"SERVERID":{"key":"SERVERID","value":"d6dcdd16ac5ff39d1965783e657b37f4|1522818404|1522818404","domain":"www.cmaotai.com","path":"/","hostOnly":true,"creation":"2018-04-04T05:06:44.273Z","lastAccessed":"2018-04-04T05:06:44.273Z"}}}}