{"www.cmaotai.com":{"/":{"acw_tc":{"key":"acw_tc","value":"AQAAABktUF2q2gIAuZ3zcbrv9Q2lkO1J","domain":"www.cmaotai.com","path":"/","httpOnly":true,"hostOnly":true,"creation":"2018-04-08T01:40:38.325Z","lastAccessed":"2018-04-08T01:40:38.325Z"},"ASP.NET_SessionId":{"key":"ASP.NET_SessionId","value":"ykpg5nyf5bcvrjsz40kr41ju","domain":"www.cmaotai.com","path":"/","httpOnly":true,"hostOnly":true,"creation":"2018-04-08T01:40:38.325Z","lastAccessed":"2018-04-08T01:40:38.325Z"},"Vshop-Member":{"key":"Vshop-Member","value":"fc2eaca71e2f495f84b21d44e87349cf","expires":"2019-04-08T01:40:35.000Z","domain":"www.cmaotai.com","path":"/","hostOnly":true,"creation":"2018-04-08T01:40:38.325Z","lastAccessed":"2018-04-08T01:40:38.325Z"},"SERVERID":{"key":"SERVERID","value":"627e30f5202674772010210cac28f0e6|1523151638|1523151638","domain":"www.cmaotai.com","path":"/","hostOnly":true,"creation":"2018-04-08T01:40:38.325Z","lastAccessed":"2018-04-08T01:40:38.325Z"}}}}