{"www.cmaotai.com":{"/":{"acw_tc":{"key":"acw_tc","value":"AQAAALRMRkMiDAsAasHncrREI4j8tA9c","domain":"www.cmaotai.com","path":"/","httpOnly":true,"hostOnly":true,"creation":"2018-04-13T03:52:31.928Z","lastAccessed":"2018-04-13T03:52:31.928Z"},"ASP.NET_SessionId":{"key":"ASP.NET_SessionId","value":"3r4awovdx0gfcbzbihj1jtu0","domain":"www.cmaotai.com","path":"/","httpOnly":true,"hostOnly":true,"creation":"2018-04-13T03:52:31.928Z","lastAccessed":"2018-04-13T03:52:31.928Z"},"Vshop-Member":{"key":"Vshop-Member","value":"a2b318d08f5e4f0296f220733e47b829","expires":"2019-04-13T03:52:32.000Z","domain":"www.cmaotai.com","path":"/","hostOnly":true,"creation":"2018-04-13T03:52:31.928Z","lastAccessed":"2018-04-13T03:52:31.928Z"},"SERVERID":{"key":"SERVERID","value":"dd0e8d182c58be79b01ce789b76259bc|1523591550|1523591550","domain":"www.cmaotai.com","path":"/","hostOnly":true,"creation":"2018-04-13T03:52:31.928Z","lastAccessed":"2018-04-13T03:52:31.928Z"}}}}