{"www.cmaotai.com":{"/":{"acw_tc":{"key":"acw_tc","value":"AQAAAHtYpTcKugwA1XOpPA0IYXCqnNuU","domain":"www.cmaotai.com","path":"/","httpOnly":true,"hostOnly":true,"creation":"2018-04-11T02:37:16.948Z","lastAccessed":"2018-04-11T02:37:16.948Z"},"ASP.NET_SessionId":{"key":"ASP.NET_SessionId","value":"y1zlqxtb2ehnwjj1x4ldoos4","domain":"www.cmaotai.com","path":"/","httpOnly":true,"hostOnly":true,"creation":"2018-04-11T02:37:16.948Z","lastAccessed":"2018-04-11T02:37:16.948Z"},"Vshop-Member":{"key":"Vshop-Member","value":"eeadfb232af3445cac881e6ef0f5a064","expires":"2019-04-11T02:37:16.000Z","domain":"www.cmaotai.com","path":"/","hostOnly":true,"creation":"2018-04-11T02:37:16.948Z","lastAccessed":"2018-04-11T02:37:16.948Z"},"SERVERID":{"key":"SERVERID","value":"8438f30ad0357ca7b03a23fe6e9923a1|1523414236|1523414236","domain":"www.cmaotai.com","path":"/","hostOnly":true,"creation":"2018-04-11T02:37:16.948Z","lastAccessed":"2018-04-11T02:37:16.948Z"}}}}