{"www.cmaotai.com":{"/":{"acw_tc":{"key":"acw_tc","value":"AQAAADL6rBuQugoAcUjmc0LKiRM9PkyH","domain":"www.cmaotai.com","path":"/","httpOnly":true,"hostOnly":true,"creation":"2018-04-25T05:23:36.810Z","lastAccessed":"2018-04-25T05:23:36.810Z"},"ASP.NET_SessionId":{"key":"ASP.NET_SessionId","value":"ljuuxzu3lz1my2btq3hqw4fa","domain":"www.cmaotai.com","path":"/","httpOnly":true,"hostOnly":true,"creation":"2018-04-25T05:23:36.811Z","lastAccessed":"2018-04-25T05:23:36.811Z"},"Vshop-Member":{"key":"Vshop-Member","value":"38631c2f23f04482933ff59f2a2de963","expires":"2019-04-25T05:23:36.000Z","domain":"www.cmaotai.com","path":"/","hostOnly":true,"creation":"2018-04-25T05:23:36.811Z","lastAccessed":"2018-04-25T05:23:36.811Z"},"SERVERID":{"key":"SERVERID","value":"73717107c680adffd3c04c75b05bf592|1524633816|1524633816","domain":"www.cmaotai.com","path":"/","hostOnly":true,"creation":"2018-04-25T05:23:36.811Z","lastAccessed":"2018-04-25T05:23:36.811Z"}}}}