{"www.cmaotai.com":{"/":{"acw_tc":{"key":"acw_tc","value":"AQAAAANvH1ZAPQ8A6l5H3/jBvSJyAiwM","domain":"www.cmaotai.com","path":"/","httpOnly":true,"hostOnly":true,"creation":"2018-05-21T01:34:05.092Z","lastAccessed":"2018-05-21T01:34:05.092Z"},"ASP.NET_SessionId":{"key":"ASP.NET_SessionId","value":"bcck3gdog4rc5pkqaxhnk4dg","domain":"www.cmaotai.com","path":"/","httpOnly":true,"hostOnly":true,"creation":"2018-05-21T01:34:05.092Z","lastAccessed":"2018-05-21T01:34:05.092Z"},"Vshop-Member":{"key":"Vshop-Member","value":"192fa203ba994bef9f4763db2a3bdf2c","expires":"2019-05-21T01:34:05.000Z","domain":"www.cmaotai.com","path":"/","hostOnly":true,"creation":"2018-05-21T01:34:05.093Z","lastAccessed":"2018-05-21T01:34:05.093Z"},"SERVERID":{"key":"SERVERID","value":"05fa188dd199f7a27f57ebc8ec96a90d|1526866445|1526866445","domain":"www.cmaotai.com","path":"/","hostOnly":true,"creation":"2018-05-21T01:34:05.093Z","lastAccessed":"2018-05-21T01:34:05.093Z"}}}}