{"www.cmaotai.com":{"/":{"acw_tc":{"key":"acw_tc","value":"AQAAAP4C9m+rmwwAs+5eL/slwzCqdY1X","domain":"www.cmaotai.com","path":"/","httpOnly":true,"hostOnly":true,"creation":"2018-05-25T11:38:34.860Z","lastAccessed":"2018-05-25T11:38:34.860Z"},"ASP.NET_SessionId":{"key":"ASP.NET_SessionId","value":"goz05tw0xnkew2q01tqif1kx","domain":"www.cmaotai.com","path":"/","httpOnly":true,"hostOnly":true,"creation":"2018-05-25T11:38:34.861Z","lastAccessed":"2018-05-25T11:38:34.861Z"},"Vshop-Member":{"key":"Vshop-Member","value":"d04a5b3464b1416bac511a8b43818f72","expires":"2019-05-25T11:38:34.000Z","domain":"www.cmaotai.com","path":"/","hostOnly":true,"creation":"2018-05-25T11:38:34.861Z","lastAccessed":"2018-05-25T11:38:34.861Z"},"SERVERID":{"key":"SERVERID","value":"dd0e8d182c58be79b01ce789b76259bc|1527248314|1527248314","domain":"www.cmaotai.com","path":"/","hostOnly":true,"creation":"2018-05-25T11:38:34.861Z","lastAccessed":"2018-05-25T11:38:34.861Z"}}}}