{"www.cmaotai.com":{"/":{"acw_tc":{"key":"acw_tc","value":"AQAAAJkJNG0ARw4ANepAddDtHBbPmVie","domain":"www.cmaotai.com","path":"/","httpOnly":true,"hostOnly":true,"creation":"2018-04-14T04:17:28.196Z","lastAccessed":"2018-04-14T04:17:28.196Z"},"ASP.NET_SessionId":{"key":"ASP.NET_SessionId","value":"luorgrsuxecw5wy2txawecss","domain":"www.cmaotai.com","path":"/","httpOnly":true,"hostOnly":true,"creation":"2018-04-14T04:17:28.196Z","lastAccessed":"2018-04-14T04:17:28.196Z"},"Vshop-Member":{"key":"Vshop-Member","value":"e9439447e0ed4f95b8b71ac3fbc6fca6","expires":"2019-04-14T04:17:28.000Z","domain":"www.cmaotai.com","path":"/","hostOnly":true,"creation":"2018-04-14T04:17:28.196Z","lastAccessed":"2018-04-14T04:17:28.196Z"},"SERVERID":{"key":"SERVERID","value":"73717107c680adffd3c04c75b05bf592|1523679447|1523679447","domain":"www.cmaotai.com","path":"/","hostOnly":true,"creation":"2018-04-14T04:17:28.196Z","lastAccessed":"2018-04-14T04:17:28.196Z"}}}}