{"www.cmaotai.com":{"/":{"acw_tc":{"key":"acw_tc","value":"AQAAALkPxzdBKwAA0jx7cVLzxHdHJrHj","domain":"www.cmaotai.com","path":"/","httpOnly":true,"hostOnly":true,"creation":"2018-04-25T15:46:45.095Z","lastAccessed":"2018-04-25T15:46:45.095Z"},"ASP.NET_SessionId":{"key":"ASP.NET_SessionId","value":"mx2vu2lzxe3zr0mzrisjw5on","domain":"www.cmaotai.com","path":"/","httpOnly":true,"hostOnly":true,"creation":"2018-04-25T15:46:45.096Z","lastAccessed":"2018-04-25T15:46:45.096Z"}}}}ERVERID":{"key":"SERVERID","value":"19df48d02d2df737cbba18bd9d142364|1524671205|1524671205","domain":"www.cmaotai.com","path":"/","hostOnly":true,"creation":"2018-04-25T15:46:45.096Z","lastAccessed":"2018-04-25T15:46:45.096Z"}}}}