{"www.cmaotai.com":{"/":{"acw_tc":{"key":"acw_tc","value":"AQAAAEi8C012CAkA6l5H3wxxr2+yf/jQ","domain":"www.cmaotai.com","path":"/","httpOnly":true,"hostOnly":true,"creation":"2018-06-04T06:49:19.621Z","lastAccessed":"2018-06-04T06:49:19.621Z"},"ASP.NET_SessionId":{"key":"ASP.NET_SessionId","value":"z1zac5kuge33tirgcwjhgi2w","domain":"www.cmaotai.com","path":"/","httpOnly":true,"hostOnly":true,"creation":"2018-06-04T06:49:19.621Z","lastAccessed":"2018-06-04T06:49:19.621Z"},"SERVERID":{"key":"SERVERID","value":"8438f30ad0357ca7b03a23fe6e9923a1|1528094959|1528094959","domain":"www.cmaotai.com","path":"/","hostOnly":true,"creation":"2018-06-04T06:49:19.621Z","lastAccessed":"2018-06-04T06:49:19.621Z"}}}}