{"www.cmaotai.com":{"/":{"acw_tc":{"key":"acw_tc","value":"AQAAAFUBpGAGiQAAVz7fct2P8DYIpi0j","domain":"www.cmaotai.com","path":"/","httpOnly":true,"hostOnly":true,"creation":"2018-04-13T03:52:41.112Z","lastAccessed":"2018-04-13T03:52:41.112Z"},"ASP.NET_SessionId":{"key":"ASP.NET_SessionId","value":"tyf0ml4frss5uc3kxuq4igdm","domain":"www.cmaotai.com","path":"/","httpOnly":true,"hostOnly":true,"creation":"2018-04-13T03:52:41.113Z","lastAccessed":"2018-04-13T03:52:41.113Z"},"Vshop-Member":{"key":"Vshop-Member","value":"d02254c3880d4fc7a7a4c279dbd7b010","expires":"2019-04-13T03:52:41.000Z","domain":"www.cmaotai.com","path":"/","hostOnly":true,"creation":"2018-04-13T03:52:41.113Z","lastAccessed":"2018-04-13T03:52:41.113Z"},"SERVERID":{"key":"SERVERID","value":"e0be7116fc95174c0c92660b6cc51b85|1523591561|1523591561","domain":"www.cmaotai.com","path":"/","hostOnly":true,"creation":"2018-04-13T03:52:41.113Z","lastAccessed":"2018-04-13T03:52:41.113Z"}}}}