{"www.cmaotai.com":{"/":{"acw_tc":{"key":"acw_tc","value":"AQAAADvJyyA7+wgATuwicwclEMXBPlMd","domain":"www.cmaotai.com","path":"/","httpOnly":true,"hostOnly":true,"creation":"2018-05-20T09:40:37.710Z","lastAccessed":"2018-05-20T09:40:37.710Z"},"ASP.NET_SessionId":{"key":"ASP.NET_SessionId","value":"4flvu0h4rllxr52qhagyagp5","domain":"www.cmaotai.com","path":"/","httpOnly":true,"hostOnly":true,"creation":"2018-05-20T09:40:37.710Z","lastAccessed":"2018-05-20T09:40:37.710Z"},"Vshop-Member":{"key":"Vshop-Member","value":"0bb52a95125343aba51241e897df657b","expires":"2019-05-20T09:40:37.000Z","domain":"www.cmaotai.com","path":"/","hostOnly":true,"creation":"2018-05-20T09:40:37.710Z","lastAccessed":"2018-05-20T09:40:37.710Z"},"SERVERID":{"key":"SERVERID","value":"dd0e8d182c58be79b01ce789b76259bc|1526809237|1526809237","domain":"www.cmaotai.com","path":"/","hostOnly":true,"creation":"2018-05-20T09:40:37.711Z","lastAccessed":"2018-05-20T09:40:37.711Z"}}}}