{"www.cmaotai.com":{"/":{"acw_tc":{"key":"acw_tc","value":"AQAAAGPX2Fg+EAkATuwic5Zw3BKvSdw1","domain":"www.cmaotai.com","path":"/","httpOnly":true,"hostOnly":true,"creation":"2018-05-20T09:40:36.696Z","lastAccessed":"2018-05-20T09:40:36.696Z"},"ASP.NET_SessionId":{"key":"ASP.NET_SessionId","value":"qtpyndjxunva20hwe0xdbnff","domain":"www.cmaotai.com","path":"/","httpOnly":true,"hostOnly":true,"creation":"2018-05-20T09:40:36.697Z","lastAccessed":"2018-05-20T09:40:36.697Z"},"Vshop-Member":{"key":"Vshop-Member","value":"13650c9df9b64a27bea5cba519a6b1bc","expires":"2019-05-20T09:40:36.000Z","domain":"www.cmaotai.com","path":"/","hostOnly":true,"creation":"2018-05-20T09:40:36.697Z","lastAccessed":"2018-05-20T09:40:36.697Z"},"SERVERID":{"key":"SERVERID","value":"1e1f01ab954be5273c933e00471b178a|1526809236|1526809236","domain":"www.cmaotai.com","path":"/","hostOnly":true,"creation":"2018-05-20T09:40:36.697Z","lastAccessed":"2018-05-20T09:40:36.697Z"}}}}