{"www.cmaotai.com":{"/":{"acw_tc":{"key":"acw_tc","value":"AQAAAFUkVgZpewsAst1vak/Rp7jJXqE7","domain":"www.cmaotai.com","path":"/","httpOnly":true,"hostOnly":true,"creation":"2018-04-11T08:50:57.056Z","lastAccessed":"2018-04-11T08:50:57.056Z"},"ASP.NET_SessionId":{"key":"ASP.NET_SessionId","value":"3dvjfndr5ng4cnbtzhe1h0el","domain":"www.cmaotai.com","path":"/","httpOnly":true,"hostOnly":true,"creation":"2018-04-11T08:50:57.057Z","lastAccessed":"2018-04-11T08:50:57.057Z"},"Vshop-Member":{"key":"Vshop-Member","value":"81468d7b61cf48e697c062354adc658a","expires":"2019-04-11T08:50:57.000Z","domain":"www.cmaotai.com","path":"/","hostOnly":true,"creation":"2018-04-11T08:50:57.057Z","lastAccessed":"2018-04-11T08:50:57.057Z"},"SERVERID":{"key":"SERVERID","value":"627e30f5202674772010210cac28f0e6|1523436655|1523436655","domain":"www.cmaotai.com","path":"/","hostOnly":true,"creation":"2018-04-11T08:50:57.057Z","lastAccessed":"2018-04-11T08:50:57.057Z"}}}}