{"www.cmaotai.com":{"/":{"acw_tc":{"key":"acw_tc","value":"AQAAAL53ikMeVwsAuaPbc/Hm+MfdA4b3","domain":"www.cmaotai.com","path":"/","httpOnly":true,"hostOnly":true,"creation":"2018-04-15T16:27:22.870Z","lastAccessed":"2018-04-15T16:27:22.870Z"},"ASP.NET_SessionId":{"key":"ASP.NET_SessionId","value":"beaq100f1b32bbc4zsvjnecb","domain":"www.cmaotai.com","path":"/","httpOnly":true,"hostOnly":true,"creation":"2018-04-15T16:27:22.870Z","lastAccessed":"2018-04-15T16:27:22.870Z"},"Vshop-Member":{"key":"Vshop-Member","value":"b872e76e75684b83932c2ff705b85517","expires":"2019-04-15T16:27:22.000Z","domain":"www.cmaotai.com","path":"/","hostOnly":true,"creation":"2018-04-15T16:27:22.871Z","lastAccessed":"2018-04-15T16:27:22.871Z"},"SERVERID":{"key":"SERVERID","value":"73717107c680adffd3c04c75b05bf592|1523809642|1523809642","domain":"www.cmaotai.com","path":"/","hostOnly":true,"creation":"2018-04-15T16:27:22.871Z","lastAccessed":"2018-04-15T16:27:22.871Z"}}}}