{"www.cmaotai.com":{"/":{"acw_tc":{"key":"acw_tc","value":"AQAAAO4sKx4lRQYA6l5H3zgqmB2AJcVw","domain":"www.cmaotai.com","path":"/","httpOnly":true,"hostOnly":true,"creation":"2018-05-21T01:41:12.433Z","lastAccessed":"2018-05-21T01:41:12.433Z"},"ASP.NET_SessionId":{"key":"ASP.NET_SessionId","value":"op5gguezq0334dsf41kezfuk","domain":"www.cmaotai.com","path":"/","httpOnly":true,"hostOnly":true,"creation":"2018-05-21T01:41:12.433Z","lastAccessed":"2018-05-21T01:41:12.433Z"},"Vshop-Member":{"key":"Vshop-Member","value":"0005245bbac543068bbc42b7b3aaf52f","expires":"2019-05-21T01:41:12.000Z","domain":"www.cmaotai.com","path":"/","hostOnly":true,"creation":"2018-05-21T01:41:12.433Z","lastAccessed":"2018-05-21T01:41:12.433Z"},"SERVERID":{"key":"SERVERID","value":"627e30f5202674772010210cac28f0e6|1526866872|1526866872","domain":"www.cmaotai.com","path":"/","hostOnly":true,"creation":"2018-05-21T01:41:12.434Z","lastAccessed":"2018-05-21T01:41:12.434Z"}}}}