{"www.cmaotai.com":{"/":{"acw_tc":{"key":"acw_tc","value":"AQAAAACqoESMZAMA6l5H3yQGA3JlCq0R","domain":"www.cmaotai.com","path":"/","httpOnly":true,"hostOnly":true,"creation":"2018-05-21T01:40:57.228Z","lastAccessed":"2018-05-21T01:40:57.228Z"},"ASP.NET_SessionId":{"key":"ASP.NET_SessionId","value":"rproynyqib0nh3giq0v1lhoa","domain":"www.cmaotai.com","path":"/","httpOnly":true,"hostOnly":true,"creation":"2018-05-21T01:40:57.228Z","lastAccessed":"2018-05-21T01:40:57.228Z"},"Vshop-Member":{"key":"Vshop-Member","value":"b5c99ff1f7954c3baa298ca97c142e4a","expires":"2019-05-21T01:40:57.000Z","domain":"www.cmaotai.com","path":"/","hostOnly":true,"creation":"2018-05-21T01:40:57.228Z","lastAccessed":"2018-05-21T01:40:57.228Z"},"SERVERID":{"key":"SERVERID","value":"1b9bd15d33a2062233e6a70bd3d8dc61|1526866857|1526866857","domain":"www.cmaotai.com","path":"/","hostOnly":true,"creation":"2018-05-21T01:40:57.228Z","lastAccessed":"2018-05-21T01:40:57.228Z"}}}}