{"www.cmaotai.com":{"/":{"acw_tc":{"key":"acw_tc","value":"AQAAAFuyAzU5OwoA6l5H35nDaXr2R3LB","domain":"www.cmaotai.com","path":"/","httpOnly":true,"hostOnly":true,"creation":"2018-05-21T01:41:10.702Z","lastAccessed":"2018-05-21T01:41:10.702Z"},"ASP.NET_SessionId":{"key":"ASP.NET_SessionId","value":"gxu2bbk4aegnbdi3grvg2ljc","domain":"www.cmaotai.com","path":"/","httpOnly":true,"hostOnly":true,"creation":"2018-05-21T01:41:10.702Z","lastAccessed":"2018-05-21T01:41:10.702Z"},"Vshop-Member":{"key":"Vshop-Member","value":"7dc87a9b235141638536f0043fe0f278","expires":"2019-05-21T01:41:11.000Z","domain":"www.cmaotai.com","path":"/","hostOnly":true,"creation":"2018-05-21T01:41:10.702Z","lastAccessed":"2018-05-21T01:41:10.702Z"},"SERVERID":{"key":"SERVERID","value":"d6dcdd16ac5ff39d1965783e657b37f4|1526866870|1526866870","domain":"www.cmaotai.com","path":"/","hostOnly":true,"creation":"2018-05-21T01:41:10.702Z","lastAccessed":"2018-05-21T01:41:10.702Z"}}}}