{"www.cmaotai.com":{"/":{"acw_tc":{"key":"acw_tc","value":"AQAAADt2Hj6GGQ8ATuwiczizYz6S9Fi0","domain":"www.cmaotai.com","path":"/","httpOnly":true,"hostOnly":true,"creation":"2018-05-20T09:51:32.057Z","lastAccessed":"2018-05-20T09:51:32.057Z"},"ASP.NET_SessionId":{"key":"ASP.NET_SessionId","value":"d2qjzjvqwdllsov1buff33vc","domain":"www.cmaotai.com","path":"/","httpOnly":true,"hostOnly":true,"creation":"2018-05-20T09:51:32.057Z","lastAccessed":"2018-05-20T09:51:32.057Z"},"Vshop-Member":{"key":"Vshop-Member","value":"383d0a33155242778c5f32970a05a786","expires":"2019-05-20T09:51:31.000Z","domain":"www.cmaotai.com","path":"/","hostOnly":true,"creation":"2018-05-20T09:51:32.057Z","lastAccessed":"2018-05-20T09:51:32.057Z"},"SERVERID":{"key":"SERVERID","value":"2fa397870239218a49136d91e984b8ea|1526809892|1526809892","domain":"www.cmaotai.com","path":"/","hostOnly":true,"creation":"2018-05-20T09:51:32.058Z","lastAccessed":"2018-05-20T09:51:32.058Z"}}}}