{"www.cmaotai.com":{"/":{"acw_tc":{"key":"acw_tc","value":"AQAAAE/i1zCzHwUA6l5H39CWVN9FAM6v","domain":"www.cmaotai.com","path":"/","httpOnly":true,"hostOnly":true,"creation":"2018-06-04T06:51:40.359Z","lastAccessed":"2018-06-04T06:51:40.359Z"},"ASP.NET_SessionId":{"key":"ASP.NET_SessionId","value":"wotkjebwn5woyjxynej2baez","domain":"www.cmaotai.com","path":"/","httpOnly":true,"hostOnly":true,"creation":"2018-06-04T06:51:40.359Z","lastAccessed":"2018-06-04T06:51:40.359Z"},"SERVERID":{"key":"SERVERID","value":"8438f30ad0357ca7b03a23fe6e9923a1|1528095100|1528095100","domain":"www.cmaotai.com","path":"/","hostOnly":true,"creation":"2018-06-04T06:51:40.359Z","lastAccessed":"2018-06-04T06:51:40.359Z"}}}}