{"www.cmaotai.com":{"/":{"acw_tc":{"key":"acw_tc","value":"AQAAABX9LVvVOggA6l5H3xrN8LYd7EHT","domain":"www.cmaotai.com","path":"/","httpOnly":true,"hostOnly":true,"creation":"2018-05-24T00:01:32.247Z","lastAccessed":"2018-05-24T00:01:32.247Z"},"ASP.NET_SessionId":{"key":"ASP.NET_SessionId","value":"dcq2teiuma0pwfzj4c41gcp2","domain":"www.cmaotai.com","path":"/","httpOnly":true,"hostOnly":true,"creation":"2018-05-24T00:01:32.247Z","lastAccessed":"2018-05-24T00:01:32.247Z"},"Vshop-Member":{"key":"Vshop-Member","value":"0ab570624fea49c7aaf032368833b386","expires":"2019-05-24T00:00:50.000Z","domain":"www.cmaotai.com","path":"/","hostOnly":true,"creation":"2018-05-24T00:01:32.247Z","lastAccessed":"2018-05-24T00:01:32.247Z"},"SERVERID":{"key":"SERVERID","value":"d6dcdd16ac5ff39d1965783e657b37f4|1527120050|1527120050","domain":"www.cmaotai.com","path":"/","hostOnly":true,"creation":"2018-05-24T00:01:32.247Z","lastAccessed":"2018-05-24T00:01:32.247Z"}}}}