{"www.cmaotai.com":{"/":{"acw_tc":{"key":"acw_tc","value":"AQAAAEhs+lhyjgMA6l5H36hGWdsZfhCC","domain":"www.cmaotai.com","path":"/","httpOnly":true,"hostOnly":true,"creation":"2018-05-21T01:45:48.282Z","lastAccessed":"2018-05-21T01:45:48.282Z"},"ASP.NET_SessionId":{"key":"ASP.NET_SessionId","value":"kypnwig2f1nmbfmgsvk44atq","domain":"www.cmaotai.com","path":"/","httpOnly":true,"hostOnly":true,"creation":"2018-05-21T01:45:48.282Z","lastAccessed":"2018-05-21T01:45:48.282Z"},"Vshop-Member":{"key":"Vshop-Member","value":"a0ca97138d6543108718c6616abb7bac","expires":"2019-05-21T01:45:48.000Z","domain":"www.cmaotai.com","path":"/","hostOnly":true,"creation":"2018-05-21T01:45:48.282Z","lastAccessed":"2018-05-21T01:45:48.282Z"},"SERVERID":{"key":"SERVERID","value":"1b9bd15d33a2062233e6a70bd3d8dc61|1526867148|1526867148","domain":"www.cmaotai.com","path":"/","hostOnly":true,"creation":"2018-05-21T01:45:48.282Z","lastAccessed":"2018-05-21T01:45:48.282Z"}}}}