{"www.cmaotai.com":{"/":{"acw_tc":{"key":"acw_tc","value":"AQAAAJFprjlIbgIATuwic9+kpyupJziN","domain":"www.cmaotai.com","path":"/","httpOnly":true,"hostOnly":true,"creation":"2018-05-20T09:51:41.256Z","lastAccessed":"2018-05-20T09:51:41.256Z"},"ASP.NET_SessionId":{"key":"ASP.NET_SessionId","value":"3y5m1isqcvncjgrp2kol0m0k","domain":"www.cmaotai.com","path":"/","httpOnly":true,"hostOnly":true,"creation":"2018-05-20T09:51:41.256Z","lastAccessed":"2018-05-20T09:51:41.256Z"},"Vshop-Member":{"key":"Vshop-Member","value":"7ba79b685172454686e4865146dd02d3","expires":"2019-05-20T09:51:41.000Z","domain":"www.cmaotai.com","path":"/","hostOnly":true,"creation":"2018-05-20T09:51:41.256Z","lastAccessed":"2018-05-20T09:51:41.256Z"},"SERVERID":{"key":"SERVERID","value":"05fa188dd199f7a27f57ebc8ec96a90d|1526809901|1526809901","domain":"www.cmaotai.com","path":"/","hostOnly":true,"creation":"2018-05-20T09:51:41.257Z","lastAccessed":"2018-05-20T09:51:41.257Z"}}}}