{"www.cmaotai.com":{"/":{"acw_tc":{"key":"acw_tc","value":"AQAAAKILIknwRgkATuwicwW8DpvY3QmO","domain":"www.cmaotai.com","path":"/","httpOnly":true,"hostOnly":true,"creation":"2018-05-20T09:51:42.728Z","lastAccessed":"2018-05-20T09:51:42.728Z"},"ASP.NET_SessionId":{"key":"ASP.NET_SessionId","value":"pp1ngbzmz2ngcrr3m3ict0tg","domain":"www.cmaotai.com","path":"/","httpOnly":true,"hostOnly":true,"creation":"2018-05-20T09:51:42.728Z","lastAccessed":"2018-05-20T09:51:42.728Z"},"Vshop-Member":{"key":"Vshop-Member","value":"e4468b4ec97a40128804ab16b3b24696","expires":"2019-05-20T09:51:42.000Z","domain":"www.cmaotai.com","path":"/","hostOnly":true,"creation":"2018-05-20T09:51:42.728Z","lastAccessed":"2018-05-20T09:51:42.728Z"},"SERVERID":{"key":"SERVERID","value":"19df48d02d2df737cbba18bd9d142364|1526809902|1526809902","domain":"www.cmaotai.com","path":"/","hostOnly":true,"creation":"2018-05-20T09:51:42.728Z","lastAccessed":"2018-05-20T09:51:42.728Z"}}}}