{"www.cmaotai.com":{"/":{"acw_tc":{"key":"acw_tc","value":"AQAAAJouaCFM3AUAQ+nVc05BhuFf4LS6","domain":"www.cmaotai.com","path":"/","httpOnly":true,"hostOnly":true,"creation":"2018-04-24T02:00:41.665Z","lastAccessed":"2018-04-24T02:00:41.665Z"},"ASP.NET_SessionId":{"key":"ASP.NET_SessionId","value":"e1bjiaz11e2xqa1laujjayow","domain":"www.cmaotai.com","path":"/","httpOnly":true,"hostOnly":true,"creation":"2018-04-24T02:00:41.665Z","lastAccessed":"2018-04-24T02:00:41.665Z"},"Vshop-Member":{"key":"Vshop-Member","value":"7343c09a8c4c4488897dc4b8b59ef968","expires":"2019-04-24T02:00:42.000Z","domain":"www.cmaotai.com","path":"/","hostOnly":true,"creation":"2018-04-24T02:00:41.665Z","lastAccessed":"2018-04-24T02:00:41.665Z"},"SERVERID":{"key":"SERVERID","value":"1b9bd15d33a2062233e6a70bd3d8dc61|1524535241|1524535241","domain":"www.cmaotai.com","path":"/","hostOnly":true,"creation":"2018-04-24T02:00:41.665Z","lastAccessed":"2018-04-24T02:00:41.665Z"}}}}