{"www.cmaotai.com":{"/":{"acw_tc":{"key":"acw_tc","value":"AQAAAGJr6ymkYQAA6l5H3+5hzQ9Rp8Sx","domain":"www.cmaotai.com","path":"/","httpOnly":true,"hostOnly":true,"creation":"2018-05-29T00:50:56.999Z","lastAccessed":"2018-05-29T00:50:56.999Z"},"ASP.NET_SessionId":{"key":"ASP.NET_SessionId","value":"zb5uvtq5fj3cedmm3ab34amr","domain":"www.cmaotai.com","path":"/","httpOnly":true,"hostOnly":true,"creation":"2018-05-29T00:50:56.999Z","lastAccessed":"2018-05-29T00:50:56.999Z"},"Vshop-Member":{"key":"Vshop-Member","value":"1c8da161ae794d6baf6d3975fc2b3951","expires":"2019-05-29T00:50:57.000Z","domain":"www.cmaotai.com","path":"/","hostOnly":true,"creation":"2018-05-29T00:50:56.999Z","lastAccessed":"2018-05-29T00:50:56.999Z"},"SERVERID":{"key":"SERVERID","value":"19df48d02d2df737cbba18bd9d142364|1527555057|1527555057","domain":"www.cmaotai.com","path":"/","hostOnly":true,"creation":"2018-05-29T00:50:56.999Z","lastAccessed":"2018-05-29T00:50:56.999Z"}}}}