{"www.cmaotai.com":{"/":{"acw_tc":{"key":"acw_tc","value":"AQAAAIdk7Q//QQ8A6l5H3yBzrxteXQug","domain":"www.cmaotai.com","path":"/","httpOnly":true,"hostOnly":true,"creation":"2018-05-24T02:11:38.014Z","lastAccessed":"2018-05-24T02:11:38.014Z"},"ASP.NET_SessionId":{"key":"ASP.NET_SessionId","value":"pdhangol5lawbk1ke1eixrob","domain":"www.cmaotai.com","path":"/","httpOnly":true,"hostOnly":true,"creation":"2018-05-24T02:11:38.014Z","lastAccessed":"2018-05-24T02:11:38.014Z"},"Vshop-Member":{"key":"Vshop-Member","value":"3631c3300bd5437f8ae35c9d21c0d5d1","expires":"2019-05-24T02:11:38.000Z","domain":"www.cmaotai.com","path":"/","hostOnly":true,"creation":"2018-05-24T02:11:38.014Z","lastAccessed":"2018-05-24T02:11:38.014Z"},"SERVERID":{"key":"SERVERID","value":"d6dcdd16ac5ff39d1965783e657b37f4|1527127898|1527127898","domain":"www.cmaotai.com","path":"/","hostOnly":true,"creation":"2018-05-24T02:11:38.015Z","lastAccessed":"2018-05-24T02:11:38.015Z"}}}}