{"www.cmaotai.com":{"/":{"acw_tc":{"key":"acw_tc","value":"AQAAAFjvIWuoRAMA6l5H35Xdi7TkVDL/","domain":"www.cmaotai.com","path":"/","httpOnly":true,"hostOnly":true,"creation":"2018-05-29T00:51:05.207Z","lastAccessed":"2018-05-29T00:51:05.207Z"},"ASP.NET_SessionId":{"key":"ASP.NET_SessionId","value":"biqh3x35m55kcaqxatgwdnru","domain":"www.cmaotai.com","path":"/","httpOnly":true,"hostOnly":true,"creation":"2018-05-29T00:51:05.207Z","lastAccessed":"2018-05-29T00:51:05.207Z"}}}}ERVERID":{"key":"SERVERID","value":"73717107c680adffd3c04c75b05bf592|1527555065|1527555065","domain":"www.cmaotai.com","path":"/","hostOnly":true,"creation":"2018-05-29T00:51:05.207Z","lastAccessed":"2018-05-29T00:51:05.207Z"}}}}