{"www.cmaotai.com":{"/":{"acw_tc":{"key":"acw_tc","value":"AQAAAPpyMBoVHgcA6l5H39HtISeGUZW+","domain":"www.cmaotai.com","path":"/","httpOnly":true,"hostOnly":true,"creation":"2018-05-24T02:11:56.549Z","lastAccessed":"2018-05-24T02:11:56.549Z"},"ASP.NET_SessionId":{"key":"ASP.NET_SessionId","value":"jq0iditdvc3m2rjbn1asjlwf","domain":"www.cmaotai.com","path":"/","httpOnly":true,"hostOnly":true,"creation":"2018-05-24T02:11:56.549Z","lastAccessed":"2018-05-24T02:11:56.549Z"},"Vshop-Member":{"key":"Vshop-Member","value":"15091ed1e2584bf8902b157ffd24c1a3","expires":"2019-05-24T02:11:56.000Z","domain":"www.cmaotai.com","path":"/","hostOnly":true,"creation":"2018-05-24T02:11:56.549Z","lastAccessed":"2018-05-24T02:11:56.549Z"},"SERVERID":{"key":"SERVERID","value":"8438f30ad0357ca7b03a23fe6e9923a1|1527127916|1527127916","domain":"www.cmaotai.com","path":"/","hostOnly":true,"creation":"2018-05-24T02:11:56.549Z","lastAccessed":"2018-05-24T02:11:56.549Z"}}}}