{"www.cmaotai.com":{"/":{"acw_tc":{"key":"acw_tc","value":"AQAAAKajsk0VDgsA6l5H3/Ln1BToRFza","domain":"www.cmaotai.com","path":"/","httpOnly":true,"hostOnly":true,"creation":"2018-05-29T00:51:04.720Z","lastAccessed":"2018-05-29T00:51:04.720Z"},"ASP.NET_SessionId":{"key":"ASP.NET_SessionId","value":"jwgrfbbovizdms101dckfddo","domain":"www.cmaotai.com","path":"/","httpOnly":true,"hostOnly":true,"creation":"2018-05-29T00:51:04.720Z","lastAccessed":"2018-05-29T00:51:04.720Z"},"SERVERID":{"key":"SERVERID","value":"2fa397870239218a49136d91e984b8ea|1527555064|1527555064","domain":"www.cmaotai.com","path":"/","hostOnly":true,"creation":"2018-05-29T00:51:04.720Z","lastAccessed":"2018-05-29T00:51:04.720Z"}}}}