{"www.cmaotai.com":{"/":{"acw_tc":{"key":"acw_tc","value":"AQAAAKOwWjfSzwMAcLzKc2GzF1g3O088","domain":"www.cmaotai.com","path":"/","httpOnly":true,"hostOnly":true,"creation":"2018-04-24T01:59:51.347Z","lastAccessed":"2018-04-24T01:59:51.347Z"},"ASP.NET_SessionId":{"key":"ASP.NET_SessionId","value":"d03m05jalfosrpl2bnnqe1tu","domain":"www.cmaotai.com","path":"/","httpOnly":true,"hostOnly":true,"creation":"2018-04-24T01:59:51.347Z","lastAccessed":"2018-04-24T01:59:51.347Z"},"Vshop-Member":{"key":"Vshop-Member","value":"d847327115274c84b0d3571cd9d3ec3b","expires":"2019-04-24T01:59:51.000Z","domain":"www.cmaotai.com","path":"/","hostOnly":true,"creation":"2018-04-24T01:59:51.347Z","lastAccessed":"2018-04-24T01:59:51.347Z"},"SERVERID":{"key":"SERVERID","value":"73717107c680adffd3c04c75b05bf592|1524535191|1524535191","domain":"www.cmaotai.com","path":"/","hostOnly":true,"creation":"2018-04-24T01:59:51.347Z","lastAccessed":"2018-04-24T01:59:51.347Z"}}}}