{"www.cmaotai.com":{"/":{"acw_tc":{"key":"acw_tc","value":"AQAAAMvMQX53vQUALARFZXx1TezKEkkj","domain":"www.cmaotai.com","path":"/","httpOnly":true,"hostOnly":true,"creation":"2018-04-12T15:34:06.500Z","lastAccessed":"2018-04-12T15:34:06.500Z"},"ASP.NET_SessionId":{"key":"ASP.NET_SessionId","value":"crvmvm2hkkimfd1larlaalvr","domain":"www.cmaotai.com","path":"/","httpOnly":true,"hostOnly":true,"creation":"2018-04-12T15:34:06.501Z","lastAccessed":"2018-04-12T15:34:06.501Z"},"Vshop-Member":{"key":"Vshop-Member","value":"ce51c338057d45b09a962a952cb9fc06","expires":"2019-04-12T15:34:06.000Z","domain":"www.cmaotai.com","path":"/","hostOnly":true,"creation":"2018-04-12T15:34:06.501Z","lastAccessed":"2018-04-12T15:34:06.501Z"},"SERVERID":{"key":"SERVERID","value":"8438f30ad0357ca7b03a23fe6e9923a1|1523547246|1523547246","domain":"www.cmaotai.com","path":"/","hostOnly":true,"creation":"2018-04-12T15:34:06.501Z","lastAccessed":"2018-04-12T15:34:06.501Z"}}}}