{"www.cmaotai.com":{"/":{"acw_tc":{"key":"acw_tc","value":"AQAAAH0aOjR9bAkAK9G7PIh8lKmGq6sP","domain":"www.cmaotai.com","path":"/","httpOnly":true,"hostOnly":true,"creation":"2018-04-11T08:46:56.877Z","lastAccessed":"2018-04-11T08:46:56.877Z"},"ASP.NET_SessionId":{"key":"ASP.NET_SessionId","value":"3dvvmahhirzeyr2gwbygs0id","domain":"www.cmaotai.com","path":"/","httpOnly":true,"hostOnly":true,"creation":"2018-04-11T08:46:56.878Z","lastAccessed":"2018-04-11T08:46:56.878Z"},"Vshop-Member":{"key":"Vshop-Member","value":"433a80285cdc4c55b2b4b11a917dfe91","expires":"2019-04-11T08:46:56.000Z","domain":"www.cmaotai.com","path":"/","hostOnly":true,"creation":"2018-04-11T08:46:56.878Z","lastAccessed":"2018-04-11T08:46:56.878Z"},"SERVERID":{"key":"SERVERID","value":"dcd9be7705f12c52b59c3e649cb5f894|1523436416|1523436416","domain":"www.cmaotai.com","path":"/","hostOnly":true,"creation":"2018-04-11T08:46:56.878Z","lastAccessed":"2018-04-11T08:46:56.878Z"}}}}