{"www.cmaotai.com":{"/":{"acw_tc":{"key":"acw_tc","value":"AQAAAG7vvmyLhg4ADiK5PNpILfZSeGjT","domain":"www.cmaotai.com","path":"/","httpOnly":true,"hostOnly":true,"creation":"2018-04-10T12:55:40.070Z","lastAccessed":"2018-04-10T12:55:40.070Z"},"ASP.NET_SessionId":{"key":"ASP.NET_SessionId","value":"slm5cymjghscljquek3ljxsz","domain":"www.cmaotai.com","path":"/","httpOnly":true,"hostOnly":true,"creation":"2018-04-10T12:55:40.071Z","lastAccessed":"2018-04-10T12:55:40.071Z"},"Vshop-Member":{"key":"Vshop-Member","value":"c989f040ed534a2aa6915e7dc0d9fae8","expires":"2019-04-10T12:55:40.000Z","domain":"www.cmaotai.com","path":"/","hostOnly":true,"creation":"2018-04-10T12:55:40.071Z","lastAccessed":"2018-04-10T12:55:40.071Z"},"SERVERID":{"key":"SERVERID","value":"73717107c680adffd3c04c75b05bf592|1523364939|1523364939","domain":"www.cmaotai.com","path":"/","hostOnly":true,"creation":"2018-04-10T12:55:40.071Z","lastAccessed":"2018-04-10T12:55:40.071Z"}}}}