{"www.cmaotai.com":{"/":{"acw_tc":{"key":"acw_tc","value":"AQAAAB4DNBGb5wEA6l5H38TGuVbs41Jw","domain":"www.cmaotai.com","path":"/","httpOnly":true,"hostOnly":true,"creation":"2018-05-21T01:46:00.178Z","lastAccessed":"2018-05-21T01:46:00.178Z"},"ASP.NET_SessionId":{"key":"ASP.NET_SessionId","value":"fyrofwytmc1ficr4ab4p1bnk","domain":"www.cmaotai.com","path":"/","httpOnly":true,"hostOnly":true,"creation":"2018-05-21T01:46:00.179Z","lastAccessed":"2018-05-21T01:46:00.179Z"},"Vshop-Member":{"key":"Vshop-Member","value":"31c48873c1bb4f8db2e35ade0480e39f","expires":"2019-05-21T01:46:00.000Z","domain":"www.cmaotai.com","path":"/","hostOnly":true,"creation":"2018-05-21T01:46:00.179Z","lastAccessed":"2018-05-21T01:46:00.179Z"},"SERVERID":{"key":"SERVERID","value":"2fa397870239218a49136d91e984b8ea|1526867160|1526867160","domain":"www.cmaotai.com","path":"/","hostOnly":true,"creation":"2018-05-21T01:46:00.179Z","lastAccessed":"2018-05-21T01:46:00.179Z"}}}}