{"www.cmaotai.com":{"/":{"acw_tc":{"key":"acw_tc","value":"AQAAANA1IH/RpAsA6l5H37XoO2p0ivlP","domain":"www.cmaotai.com","path":"/","httpOnly":true,"hostOnly":true,"creation":"2018-05-24T00:03:03.430Z","lastAccessed":"2018-05-24T00:03:03.430Z"},"ASP.NET_SessionId":{"key":"ASP.NET_SessionId","value":"1wksqnxz4ysopjynchbslz2z","domain":"www.cmaotai.com","path":"/","httpOnly":true,"hostOnly":true,"creation":"2018-05-24T00:03:03.430Z","lastAccessed":"2018-05-24T00:03:03.430Z"},"Vshop-Member":{"key":"Vshop-Member","value":"7bea7797437547c180d1872953e40397","expires":"2019-05-24T00:02:21.000Z","domain":"www.cmaotai.com","path":"/","hostOnly":true,"creation":"2018-05-24T00:03:03.430Z","lastAccessed":"2018-05-24T00:03:03.430Z"},"SERVERID":{"key":"SERVERID","value":"05fa188dd199f7a27f57ebc8ec96a90d|1527120141|1527120141","domain":"www.cmaotai.com","path":"/","hostOnly":true,"creation":"2018-05-24T00:03:03.430Z","lastAccessed":"2018-05-24T00:03:03.430Z"}}}}