{"www.cmaotai.com":{"/":{"acw_tc":{"key":"acw_tc","value":"AQAAAOy2/HaBkwoATuwic2XgBTSgh+mH","domain":"www.cmaotai.com","path":"/","httpOnly":true,"hostOnly":true,"creation":"2018-05-20T10:14:26.905Z","lastAccessed":"2018-05-20T10:14:26.905Z"},"ASP.NET_SessionId":{"key":"ASP.NET_SessionId","value":"waxkd540bqoshmrkbblk3y3u","domain":"www.cmaotai.com","path":"/","httpOnly":true,"hostOnly":true,"creation":"2018-05-20T10:14:26.905Z","lastAccessed":"2018-05-20T10:14:26.905Z"},"Vshop-Member":{"key":"Vshop-Member","value":"66fafa2036114a598368f23a03598f72","expires":"2019-05-20T10:14:26.000Z","domain":"www.cmaotai.com","path":"/","hostOnly":true,"creation":"2018-05-20T10:14:26.906Z","lastAccessed":"2018-05-20T10:14:26.906Z"},"SERVERID":{"key":"SERVERID","value":"8438f30ad0357ca7b03a23fe6e9923a1|1526811266|1526811266","domain":"www.cmaotai.com","path":"/","hostOnly":true,"creation":"2018-05-20T10:14:26.906Z","lastAccessed":"2018-05-20T10:14:26.906Z"}}}}