{"www.cmaotai.com":{"/":{"acw_tc":{"key":"acw_tc","value":"AQAAAPy2QBpNEAwA6l5H3wP2p4Qa9X4R","domain":"www.cmaotai.com","path":"/","httpOnly":true,"hostOnly":true,"creation":"2018-06-04T06:54:00.864Z","lastAccessed":"2018-06-04T06:54:00.864Z"},"ASP.NET_SessionId":{"key":"ASP.NET_SessionId","value":"2aqfrmca4dic3aiwg55x0h2u","domain":"www.cmaotai.com","path":"/","httpOnly":true,"hostOnly":true,"creation":"2018-06-04T06:54:00.864Z","lastAccessed":"2018-06-04T06:54:00.864Z"},"Vshop-Member":{"key":"Vshop-Member","value":"aaa2581655374fc1ae0f862e5814c409","expires":"2019-06-04T06:54:00.000Z","domain":"www.cmaotai.com","path":"/","hostOnly":true,"creation":"2018-06-04T06:54:00.864Z","lastAccessed":"2018-06-04T06:54:00.864Z"},"SERVERID":{"key":"SERVERID","value":"2fa397870239218a49136d91e984b8ea|1528095240|1528095240","domain":"www.cmaotai.com","path":"/","hostOnly":true,"creation":"2018-06-04T06:54:00.864Z","lastAccessed":"2018-06-04T06:54:00.864Z"}}}}