{"www.cmaotai.com":{"/":{"acw_tc":{"key":"acw_tc","value":"AQAAACMTex/yBgcA6l5H33DpNCmfXX0k","domain":"www.cmaotai.com","path":"/","httpOnly":true,"hostOnly":true,"creation":"2018-05-24T00:03:10.126Z","lastAccessed":"2018-05-24T00:03:10.126Z"},"ASP.NET_SessionId":{"key":"ASP.NET_SessionId","value":"1vxkkogetfk1zzuasovvke1l","domain":"www.cmaotai.com","path":"/","httpOnly":true,"hostOnly":true,"creation":"2018-05-24T00:03:10.127Z","lastAccessed":"2018-05-24T00:03:10.127Z"},"Vshop-Member":{"key":"Vshop-Member","value":"beb37a413bd5408cb7a7545340bda9d6","expires":"2019-05-24T00:02:28.000Z","domain":"www.cmaotai.com","path":"/","hostOnly":true,"creation":"2018-05-24T00:03:10.127Z","lastAccessed":"2018-05-24T00:03:10.127Z"},"SERVERID":{"key":"SERVERID","value":"dd0e8d182c58be79b01ce789b76259bc|1527120148|1527120148","domain":"www.cmaotai.com","path":"/","hostOnly":true,"creation":"2018-05-24T00:03:10.127Z","lastAccessed":"2018-05-24T00:03:10.127Z"}}}}