{"www.cmaotai.com":{"/":{"acw_tc":{"key":"acw_tc","value":"AQAAAKHEmjR9pg0A6l5H32RfZSA+B+uw","domain":"www.cmaotai.com","path":"/","httpOnly":true,"hostOnly":true,"creation":"2018-06-04T06:54:11.936Z","lastAccessed":"2018-06-04T06:54:11.936Z"},"ASP.NET_SessionId":{"key":"ASP.NET_SessionId","value":"2gowdblds4csstrwya3wgvzq","domain":"www.cmaotai.com","path":"/","httpOnly":true,"hostOnly":true,"creation":"2018-06-04T06:54:11.936Z","lastAccessed":"2018-06-04T06:54:11.936Z"},"Vshop-Member":{"key":"Vshop-Member","value":"3fa876e05fb14e88be8578ab0cb85e0f","expires":"2019-06-04T06:54:11.000Z","domain":"www.cmaotai.com","path":"/","hostOnly":true,"creation":"2018-06-04T06:54:11.937Z","lastAccessed":"2018-06-04T06:54:11.937Z"},"SERVERID":{"key":"SERVERID","value":"19df48d02d2df737cbba18bd9d142364|1528095251|1528095251","domain":"www.cmaotai.com","path":"/","hostOnly":true,"creation":"2018-06-04T06:54:11.937Z","lastAccessed":"2018-06-04T06:54:11.937Z"}}}}