{"www.cmaotai.com":{"/":{"acw_tc":{"key":"acw_tc","value":"AQAAAOecK1v2FQEA6l5H32fINqLntkN5","domain":"www.cmaotai.com","path":"/","httpOnly":true,"hostOnly":true,"creation":"2018-05-21T01:46:11.161Z","lastAccessed":"2018-05-21T01:46:11.161Z"},"ASP.NET_SessionId":{"key":"ASP.NET_SessionId","value":"0wjilqfzg54sr1mgd25h1hnm","domain":"www.cmaotai.com","path":"/","httpOnly":true,"hostOnly":true,"creation":"2018-05-21T01:46:11.162Z","lastAccessed":"2018-05-21T01:46:11.162Z"},"Vshop-Member":{"key":"Vshop-Member","value":"a027db73551d426890b464678adff263","expires":"2019-05-21T01:46:11.000Z","domain":"www.cmaotai.com","path":"/","hostOnly":true,"creation":"2018-05-21T01:46:11.162Z","lastAccessed":"2018-05-21T01:46:11.162Z"},"SERVERID":{"key":"SERVERID","value":"627e30f5202674772010210cac28f0e6|1526867171|1526867171","domain":"www.cmaotai.com","path":"/","hostOnly":true,"creation":"2018-05-21T01:46:11.162Z","lastAccessed":"2018-05-21T01:46:11.162Z"}}}}