{"www.cmaotai.com":{"/":{"acw_tc":{"key":"acw_tc","value":"AQAAAB1JaXLtqgEASOBDcHssqKjo/XmZ","domain":"www.cmaotai.com","path":"/","httpOnly":true,"hostOnly":true,"creation":"2018-04-12T16:09:48.292Z","lastAccessed":"2018-04-12T16:09:48.292Z"},"ASP.NET_SessionId":{"key":"ASP.NET_SessionId","value":"4xbpvf0vd1exp25x21yqea54","domain":"www.cmaotai.com","path":"/","httpOnly":true,"hostOnly":true,"creation":"2018-04-12T16:09:48.292Z","lastAccessed":"2018-04-12T16:09:48.292Z"},"Vshop-Member":{"key":"Vshop-Member","value":"b2785f4f1b4547eba65f96dd124ebdd8","expires":"2019-04-12T16:09:48.000Z","domain":"www.cmaotai.com","path":"/","hostOnly":true,"creation":"2018-04-12T16:09:48.292Z","lastAccessed":"2018-04-12T16:09:48.292Z"},"SERVERID":{"key":"SERVERID","value":"494949e7eebb4b7a1681a43226a2e016|1523549388|1523549388","domain":"www.cmaotai.com","path":"/","hostOnly":true,"creation":"2018-04-12T16:09:48.295Z","lastAccessed":"2018-04-12T16:09:48.295Z"}}}}