{"www.cmaotai.com":{"/":{"acw_tc":{"key":"acw_tc","value":"AQAAAJqLKy8I6wUAZVe9elNoz/Xi8iCr","domain":"www.cmaotai.com","path":"/","httpOnly":true,"hostOnly":true,"creation":"2018-04-11T14:25:17.568Z","lastAccessed":"2018-04-11T14:25:17.568Z"},"ASP.NET_SessionId":{"key":"ASP.NET_SessionId","value":"fk4rrnl0cqjvcpyan01fxntc","domain":"www.cmaotai.com","path":"/","httpOnly":true,"hostOnly":true,"creation":"2018-04-11T14:25:17.568Z","lastAccessed":"2018-04-11T14:25:17.568Z"},"Vshop-Member":{"key":"Vshop-Member","value":"166cdbd56dd546d7859949102f832c55","expires":"2019-04-11T14:25:17.000Z","domain":"www.cmaotai.com","path":"/","hostOnly":true,"creation":"2018-04-11T14:25:17.568Z","lastAccessed":"2018-04-11T14:25:17.568Z"},"SERVERID":{"key":"SERVERID","value":"19df48d02d2df737cbba18bd9d142364|1523456717|1523456717","domain":"www.cmaotai.com","path":"/","hostOnly":true,"creation":"2018-04-11T14:25:17.568Z","lastAccessed":"2018-04-11T14:25:17.568Z"}}}}