{"www.cmaotai.com":{"/":{"acw_tc":{"key":"acw_tc","value":"AQAAAI0Y6TlPLQEADk/mc71skvQ9nfbE","domain":"www.cmaotai.com","path":"/","httpOnly":true,"hostOnly":true,"creation":"2018-04-03T13:06:35.218Z","lastAccessed":"2018-04-03T13:06:35.218Z"},"ASP.NET_SessionId":{"key":"ASP.NET_SessionId","value":"vkvgicomdlwhxxb1sp4lhlxu","domain":"www.cmaotai.com","path":"/","httpOnly":true,"hostOnly":true,"creation":"2018-04-03T13:06:35.218Z","lastAccessed":"2018-04-03T13:06:35.218Z"},"Vshop-Member":{"key":"Vshop-Member","value":"ead7af41dad7498fb9713e2e1e7f64ce","expires":"2019-04-03T13:06:32.000Z","domain":"www.cmaotai.com","path":"/","hostOnly":true,"creation":"2018-04-03T13:06:35.218Z","lastAccessed":"2018-04-03T13:06:35.218Z"},"SERVERID":{"key":"SERVERID","value":"d7ff3566a46564dfbddba0bd72787651|1522760795|1522760795","domain":"www.cmaotai.com","path":"/","hostOnly":true,"creation":"2018-04-03T13:06:35.219Z","lastAccessed":"2018-04-03T13:06:35.219Z"}}}}