{"www.cmaotai.com":{"/":{"acw_tc":{"key":"acw_tc","value":"AQAAAL0snAYuHAAAJxSiPNSOCQBqfGtz","domain":"www.cmaotai.com","path":"/","httpOnly":true,"hostOnly":true,"creation":"2018-04-11T02:38:02.238Z","lastAccessed":"2018-04-11T02:38:02.238Z"},"ASP.NET_SessionId":{"key":"ASP.NET_SessionId","value":"13otof1z5yymj0ugrmvio43r","domain":"www.cmaotai.com","path":"/","httpOnly":true,"hostOnly":true,"creation":"2018-04-11T02:38:02.238Z","lastAccessed":"2018-04-11T02:38:02.238Z"},"Vshop-Member":{"key":"Vshop-Member","value":"6e82ce2257784e9da7f99a82f33d8ca8","expires":"2019-04-11T02:38:02.000Z","domain":"www.cmaotai.com","path":"/","hostOnly":true,"creation":"2018-04-11T02:38:02.238Z","lastAccessed":"2018-04-11T02:38:02.238Z"},"SERVERID":{"key":"SERVERID","value":"73717107c680adffd3c04c75b05bf592|1523414282|1523414282","domain":"www.cmaotai.com","path":"/","hostOnly":true,"creation":"2018-04-11T02:38:02.238Z","lastAccessed":"2018-04-11T02:38:02.238Z"}}}}