{"www.cmaotai.com":{"/":{"acw_tc":{"key":"acw_tc","value":"AQAAAEfS8UC8gQUA6l5H3/TByhnkSy4G","domain":"www.cmaotai.com","path":"/","httpOnly":true,"hostOnly":true,"creation":"2018-06-04T06:04:03.410Z","lastAccessed":"2018-06-04T06:04:03.410Z"},"ASP.NET_SessionId":{"key":"ASP.NET_SessionId","value":"tq32uh43zyxjcxq4x4sor0ge","domain":"www.cmaotai.com","path":"/","httpOnly":true,"hostOnly":true,"creation":"2018-06-04T06:04:03.410Z","lastAccessed":"2018-06-04T06:04:03.410Z"},"Vshop-Member":{"key":"Vshop-Member","value":"fe39144d49ec4a6ebbcfd088069bde97","expires":"2019-06-04T06:04:03.000Z","domain":"www.cmaotai.com","path":"/","hostOnly":true,"creation":"2018-06-04T06:04:03.411Z","lastAccessed":"2018-06-04T06:04:03.411Z"},"SERVERID":{"key":"SERVERID","value":"d6dcdd16ac5ff39d1965783e657b37f4|1528092243|1528092243","domain":"www.cmaotai.com","path":"/","hostOnly":true,"creation":"2018-06-04T06:04:03.411Z","lastAccessed":"2018-06-04T06:04:03.411Z"}}}}