{"www.cmaotai.com":{"/":{"acw_tc":{"key":"acw_tc","value":"AQAAAK1O0F/RJQwA6l5H38uuGiStZILo","domain":"www.cmaotai.com","path":"/","httpOnly":true,"hostOnly":true,"creation":"2018-06-04T06:04:10.874Z","lastAccessed":"2018-06-04T06:04:10.874Z"},"ASP.NET_SessionId":{"key":"ASP.NET_SessionId","value":"p52itfs10tp1kru1he43motj","domain":"www.cmaotai.com","path":"/","httpOnly":true,"hostOnly":true,"creation":"2018-06-04T06:04:10.874Z","lastAccessed":"2018-06-04T06:04:10.874Z"},"Vshop-Member":{"key":"Vshop-Member","value":"9c3e315c9ba8459fae03dbc062b4c50b","expires":"2019-06-04T06:04:10.000Z","domain":"www.cmaotai.com","path":"/","hostOnly":true,"creation":"2018-06-04T06:04:10.874Z","lastAccessed":"2018-06-04T06:04:10.874Z"},"SERVERID":{"key":"SERVERID","value":"19df48d02d2df737cbba18bd9d142364|1528092250|1528092250","domain":"www.cmaotai.com","path":"/","hostOnly":true,"creation":"2018-06-04T06:04:10.874Z","lastAccessed":"2018-06-04T06:04:10.874Z"}}}}