{"www.cmaotai.com":{"/":{"acw_tc":{"key":"acw_tc","value":"AQAAALlVPiTzSwUAwYu6exzfXP9sJOze","domain":"www.cmaotai.com","path":"/","httpOnly":true,"hostOnly":true,"creation":"2018-04-25T00:48:05.460Z","lastAccessed":"2018-04-25T00:48:05.460Z"},"ASP.NET_SessionId":{"key":"ASP.NET_SessionId","value":"31jjrybslv2noeiu0h4bqic0","domain":"www.cmaotai.com","path":"/","httpOnly":true,"hostOnly":true,"creation":"2018-04-25T00:48:05.460Z","lastAccessed":"2018-04-25T00:48:05.460Z"},"Vshop-Member":{"key":"Vshop-Member","value":"a65b1fb239d94d92b9a8a8c3f915e010","expires":"2019-04-25T00:48:05.000Z","domain":"www.cmaotai.com","path":"/","hostOnly":true,"creation":"2018-04-25T00:48:05.460Z","lastAccessed":"2018-04-25T00:48:05.460Z"},"SERVERID":{"key":"SERVERID","value":"dd0e8d182c58be79b01ce789b76259bc|1524617285|1524617285","domain":"www.cmaotai.com","path":"/","hostOnly":true,"creation":"2018-04-25T00:48:05.461Z","lastAccessed":"2018-04-25T00:48:05.461Z"}}}}