{"www.cmaotai.com":{"/":{"acw_tc":{"key":"acw_tc","value":"AQAAALpmz0Tyiw0A6l5H3733cORDgjIN","domain":"www.cmaotai.com","path":"/","httpOnly":true,"hostOnly":true,"creation":"2018-05-24T00:11:45.578Z","lastAccessed":"2018-05-24T00:11:45.578Z"},"ASP.NET_SessionId":{"key":"ASP.NET_SessionId","value":"2nftec3loh2eaagwcae343ui","domain":"www.cmaotai.com","path":"/","httpOnly":true,"hostOnly":true,"creation":"2018-05-24T00:11:45.578Z","lastAccessed":"2018-05-24T00:11:45.578Z"},"Vshop-Member":{"key":"Vshop-Member","value":"715129c2598c4e8aaccd51b9c175a87b","expires":"2019-05-24T00:11:03.000Z","domain":"www.cmaotai.com","path":"/","hostOnly":true,"creation":"2018-05-24T00:11:45.578Z","lastAccessed":"2018-05-24T00:11:45.578Z"},"SERVERID":{"key":"SERVERID","value":"2fa397870239218a49136d91e984b8ea|1527120663|1527120663","domain":"www.cmaotai.com","path":"/","hostOnly":true,"creation":"2018-05-24T00:11:45.578Z","lastAccessed":"2018-05-24T00:11:45.578Z"}}}}