{"www.cmaotai.com":{"/":{"acw_tc":{"key":"acw_tc","value":"AQAAAKFBg2/cRQkAe0eyPCgcLLij4+sK","domain":"www.cmaotai.com","path":"/","httpOnly":true,"hostOnly":true,"creation":"2018-04-25T05:24:55.676Z","lastAccessed":"2018-04-25T05:24:55.676Z"},"ASP.NET_SessionId":{"key":"ASP.NET_SessionId","value":"qabiy2vrqwakbem5osh1gn2b","domain":"www.cmaotai.com","path":"/","httpOnly":true,"hostOnly":true,"creation":"2018-04-25T05:24:55.676Z","lastAccessed":"2018-04-25T05:24:55.676Z"},"Vshop-Member":{"key":"Vshop-Member","value":"76d89ab01f744d90859149605d45aa46","expires":"2019-04-25T05:24:55.000Z","domain":"www.cmaotai.com","path":"/","hostOnly":true,"creation":"2018-04-25T05:24:55.676Z","lastAccessed":"2018-04-25T05:24:55.676Z"},"SERVERID":{"key":"SERVERID","value":"2fa397870239218a49136d91e984b8ea|1524633895|1524633895","domain":"www.cmaotai.com","path":"/","hostOnly":true,"creation":"2018-04-25T05:24:55.676Z","lastAccessed":"2018-04-25T05:24:55.676Z"}}}}