[
    {
        "id": "141411500001",
        "name": "茅台云商河南省信阳市浉河区服务网点",
        "address": "信阳市浉河区大庆路阳光新村2号楼",
        "tel": "0376-6288833　18348495654",
        "dname": "信阳屹宏天朗实业有限公司"
    },
    {
        "id": "141411500002",
        "name": "茅台云商河南省信阳市浉河区服务网点",
        "address": "信阳市东方红大道中西段“八一商业步行街”",
        "tel": "0376-6189619",
        "dname": "河南心悦肥业有限公司"
    },
    {
        "id": "241411500001",
        "name": "茅台云商河南省信阳市信阳市服务网点",
        "address": "信阳市平桥区羊山新区新七大道77号",
        "tel": "18240511521",
        "dname": "信阳国际大酒店有限公司"
    }
]